Metadata-Version: 1.0
Name: sample-project-h
Version: 0.1.2
Summary: The funniest joke in the world
Home-page: http://github.com/hemangsk/sample=project-h
Author: Flying Circus
Author-email: flyingcircus@example.com
License: MIT
Platform: UNKNOWN
